
[
    {
        "key": "group_625a9cefab076",
        "title": "Block - Info",
        "fields": [
            {
                "key": "field_625a9d1975e0e",
                "label": "Info",
                "name": "",
                "type": "tab",
                "instructions": "",
                "required": 0,
                "conditional_logic": 0,
                "wrapper": {
                    "width": "",
                    "class": "",
                    "id": ""
                },
                "placement": "top",
                "endpoint": 0
            },
            {
                "key": "field_625a9cf775e0c",
                "label": "Title",
                "name": "blocks-title",
                "type": "text",
                "instructions": "",
                "required": 0,
                "conditional_logic": 0,
                "wrapper": {
                    "width": "",
                    "class": "",
                    "id": ""
                },
                "default_value": "",
                "placeholder": "",
                "prepend": "",
                "append": "",
                "maxlength": ""
            },
            {
                "key": "field_625a9d0775e0d",
                "label": "Summary",
                "name": "blocks-summary",
                "type": "textarea",
                "instructions": "",
                "required": 0,
                "conditional_logic": 0,
                "wrapper": {
                    "width": "",
                    "class": "",
                    "id": ""
                },
                "default_value": "",
                "placeholder": "",
                "maxlength": "",
                "rows": "",
                "new_lines": ""
            },
            {
                "key": "field_625e3afea3fed",
                "label": "Thumbnail",
                "name": "blocks-thumbnail",
                "type": "image",
                "instructions": "",
                "required": 0,
                "conditional_logic": 0,
                "wrapper": {
                    "width": "50",
                    "class": "",
                    "id": ""
                },
                "return_format": "id",
                "preview_size": "medium",
                "library": "all",
                "min_width": "",
                "min_height": "",
                "min_size": "",
                "max_width": "",
                "max_height": "",
                "max_size": "",
                "mime_types": ""
            },
            {
                "key": "field_625e3b464f5e1",
                "label": "Size",
                "name": "blocks-thumbnail-size",
                "type": "select",
                "instructions": "",
                "required": 0,
                "conditional_logic": 0,
                "wrapper": {
                    "width": "50",
                    "class": "",
                    "id": ""
                },
                "choices": {
                    "thumbnail": "thumbnail",
                    "medium": "medium",
                    "medium_large": "medium_large",
                    "large": "large",
                    "1536x1536": "1536x1536",
                    "2048x2048": "2048x2048",
                    "sidebar-featured": "sidebar-featured",
                    "genesis-singular-images": "genesis-singular-images"
                },
                "default_value": false,
                "allow_null": 0,
                "multiple": 0,
                "ui": 0,
                "return_format": "value",
                "ajax": 0,
                "placeholder": ""
            },
            {
                "key": "field_625a9d3375e0f",
                "label": "Layout",
                "name": "",
                "type": "tab",
                "instructions": "",
                "required": 0,
                "conditional_logic": 0,
                "wrapper": {
                    "width": "",
                    "class": "",
                    "id": ""
                },
                "placement": "top",
                "endpoint": 0
            },
            {
                "key": "field_625a9d5275e10",
                "label": "Template",
                "name": "blocks-template",
                "type": "select",
                "instructions": "",
                "required": 0,
                "conditional_logic": 0,
                "wrapper": {
                    "width": "",
                    "class": "",
                    "id": ""
                },
                "choices": {
                    "h1-title.php": "h1-title",
                    "orange.php": "orange",
                    "thumbnail.php": "thumbnail"
                },
                "default_value": false,
                "allow_null": 0,
                "multiple": 0,
                "ui": 0,
                "return_format": "value",
                "ajax": 0,
                "placeholder": ""
            },
            {
                "key": "field_625a9ee52cb66",
                "label": "Section Class",
                "name": "blocks-section-class",
                "type": "text",
                "instructions": "",
                "required": 0,
                "conditional_logic": 0,
                "wrapper": {
                    "width": "",
                    "class": "",
                    "id": ""
                },
                "default_value": "",
                "placeholder": "",
                "prepend": "",
                "append": "",
                "maxlength": ""
            },
            {
                "key": "field_625a9ef92cb67",
                "label": "Section Style",
                "name": "blocks-section-style",
                "type": "text",
                "instructions": "",
                "required": 0,
                "conditional_logic": 0,
                "wrapper": {
                    "width": "",
                    "class": "",
                    "id": ""
                },
                "default_value": "",
                "placeholder": "",
                "prepend": "",
                "append": "",
                "maxlength": ""
            }
        ],
        "location": [
            [
                {
                    "param": "block",
                    "operator": "==",
                    "value": "acf\/info-block"
                }
            ]
        ],
        "menu_order": 0,
        "position": "normal",
        "style": "default",
        "label_placement": "top",
        "instruction_placement": "label",
        "hide_on_screen": "",
        "active": true,
        "description": "",
        "show_in_rest": 0
    }
]